params/__init__.py
params/params.py
params_FranklinLi-0.1.0.dist-info/LICENSE
params_FranklinLi-0.1.0.dist-info/METADATA
params_FranklinLi-0.1.0.dist-info/WHEEL
params_FranklinLi-0.1.0.dist-info/top_level.txt
params_FranklinLi-0.1.0.dist-info/RECORD
