Metadata-Version: 2.1
Name: params-FranklinLi
Version: 0.1.0
Summary: Command line flags alternative for Jupyter
Home-page: https://github.com/CourierKyn/params
Author: Franklin Li
Author-email: franklin_a_h_p@qq.com
License: UNKNOWN
Platform: UNKNOWN
Classifier: Programming Language :: Python :: 3
Classifier: License :: OSI Approved :: MIT License
Classifier: Operating System :: OS Independent
Requires-Python: >=3.7
Requires-Dist: ipywidgets (>=7.5.1)
